Connectome_Spatial_Smoothing/CSS.py
Connectome_Spatial_Smoothing/__init__.py
Connectome_Spatial_Smoothing/data/templates/atlas/Glasser360.32k_fs_LR.dlabel.nii
Connectome_Spatial_Smoothing/data/templates/cifti/ones.dscalar.nii
Connectome_Spatial_Smoothing-0.1.6.dist-info/LICENSE
Connectome_Spatial_Smoothing-0.1.6.dist-info/METADATA
Connectome_Spatial_Smoothing-0.1.6.dist-info/WHEEL
Connectome_Spatial_Smoothing-0.1.6.dist-info/top_level.txt
Connectome_Spatial_Smoothing-0.1.6.dist-info/RECORD
