Metadata-Version: 2.1
Name: Connectome-Spatial-Smoothing
Version: 0.1.6
Summary: Connectome Spatial Smoothing
Home-page: https://github.com/sina-mansour/connectome-spatial-smoothing
Author: Sina Mansour L.
Author-email: sina.mansour.lakouraj@gmail.com
Project-URL: Bug Tracker, https://github.com/sina-mansour/connectome-spatial-smoothing/issues
Classifier: Programming Language :: Python :: 3
Classifier: License :: OSI Approved :: MIT License
Classifier: Operating System :: OS Independent
Requires-Python: >=3.6
License-File: LICENSE
Requires-Dist: numpy
Requires-Dist: scipy
Requires-Dist: scikit-learn
Requires-Dist: nibabel
Requires-Dist: gdist
